{
  "metadata": {
    "generated_at": "2025-09-11T03:40:27.010560",
    "client_number": "11016",
    "data_source": "BotanBot XML Export"
  },
  "client_profile": {
    "client_number": "11016",
    "search_term": "CRUISER FOOD",
    "status": "Kunde",
    "tax_number": "",
    "vat_id": "",
    "is_blocked": false,
    "price_group": "(Std.-Preis)",
    "billing_address": {
      "salutation": "",
      "name": "Cruiser Food",
      "name3": "Inh.: Hamid Entezari",
      "street": "Siebentunnelweg 14",
      "city": "Halstenbek",
      "postal_code": "25469",
      "country": "Deutschland",
      "phone": "(0 40) 80 01 08 25",
      "fax": "",
      "email": "emal20@hotmail.de"
    },
    "delivery_address": {
      "salutation": "",
      "name": "Cruiser Food",
      "name3": "Inh.: Hamid Entezari",
      "street": "Siebentunnelweg 14",
      "city": "Halstenbek",
      "postal_code": "25469",
      "country": "Deutschland",
      "phone": "(0 40) 80 01 08 25",
      "fax": "",
      "email": "emal20@hotmail.de"
    },
    "delivery_schedule": {
      "monday": "",
      "tuesday": "",
      "wednesday": "",
      "thursday": "",
      "friday": "",
      "saturday": ""
    },
    "settings": {
      "webshop_enabled": false,
      "ds_addresses": false,
      "no_pickup_app": false,
      "minimum_order_value": null,
      "articles_not_in_history": ""
    },
    "additional_addresses": [
      {
        "address_number": "0",
        "salutation": "",
        "name": "Cruiser Food",
        "name3": "Inh.: Hamid Entezari",
        "street": "Siebentunnelweg 14",
        "city": "Halstenbek",
        "postal_code": "25469",
        "country": "Deutschland",
        "phone": "(0 40) 80 01 08 25",
        "fax": "",
        "email": "emal20@hotmail.de",
        "is_default_billing": true,
        "is_default_delivery": true
      }
    ]
  },
  "order_statistics": {
    "total_orders": 0,
    "unique_articles_ordered": 0,
    "recent_orders_count": 0,
    "last_order_date": null
  },
  "order_history": []
}