{
  "metadata": {
    "generated_at": "2025-09-11T03:40:28.809294",
    "client_number": "17450",
    "data_source": "BotanBot XML Export"
  },
  "client_profile": {
    "client_number": "17450",
    "search_term": "SNACK",
    "status": "Kunde",
    "tax_number": "",
    "vat_id": "",
    "is_blocked": false,
    "price_group": "(Std.-Preis)",
    "billing_address": {
      "salutation": "Firma",
      "name": "Snack 4 you",
      "name3": "Birkandan und Tozlu GBR",
      "street": "Buchenrade 6",
      "city": "Mönkeberg",
      "postal_code": "24248",
      "country": "Deutschland",
      "phone": "(01 72) 1 87 - 19 06",
      "fax": "",
      "email": "info@snacks4you.de"
    },
    "delivery_address": {
      "salutation": "Firma",
      "name": "Snack 4 you",
      "name3": "Birkandan und Tozlu GBR",
      "street": "Buchenrade 6",
      "city": "Mönkeberg",
      "postal_code": "24248",
      "country": "Deutschland",
      "phone": "(01 72) 1 87 - 19 06",
      "fax": "",
      "email": "info@snacks4you.de"
    },
    "delivery_schedule": {
      "monday": "",
      "tuesday": "",
      "wednesday": "",
      "thursday": "",
      "friday": "",
      "saturday": ""
    },
    "settings": {
      "webshop_enabled": false,
      "ds_addresses": false,
      "no_pickup_app": false,
      "minimum_order_value": null,
      "articles_not_in_history": ""
    },
    "additional_addresses": [
      {
        "address_number": "0",
        "salutation": "Firma",
        "name": "Snack 4 you",
        "name3": "Birkandan und Tozlu GBR",
        "street": "Buchenrade 6",
        "city": "Mönkeberg",
        "postal_code": "24248",
        "country": "Deutschland",
        "phone": "(01 72) 1 87 - 19 06",
        "fax": "",
        "email": "info@snacks4you.de",
        "is_default_billing": true,
        "is_default_delivery": true
      }
    ]
  },
  "order_statistics": {
    "total_orders": 0,
    "unique_articles_ordered": 0,
    "recent_orders_count": 0,
    "last_order_date": null
  },
  "order_history": []
}