{
  "metadata": {
    "generated_at": "2025-09-11T03:40:29.101300",
    "client_number": "76017",
    "data_source": "BotanBot XML Export"
  },
  "client_profile": {
    "client_number": "76017",
    "search_term": "STOROPACK",
    "status": "Lieferant",
    "tax_number": "",
    "vat_id": "",
    "is_blocked": false,
    "price_group": "(Std.-Preis)",
    "billing_address": {
      "salutation": "Firma",
      "name": "Storopack Deutschland GmbH & Ko.KG",
      "name3": "",
      "street": "Asbrookdamm 40",
      "city": "Hamburg",
      "postal_code": "22115",
      "country": "Deutschland",
      "phone": "(0 40) 40 71 59 90",
      "fax": "(0 40) 4 07 15 99 44",
      "email": "andre.boge@storopack.com"
    },
    "delivery_address": {
      "salutation": "Firma",
      "name": "Storopack Deutschland GmbH & Ko.KG",
      "name3": "",
      "street": "Asbrookdamm 40",
      "city": "Hamburg",
      "postal_code": "22115",
      "country": "Deutschland",
      "phone": "(0 40) 40 71 59 90",
      "fax": "(0 40) 4 07 15 99 44",
      "email": "andre.boge@storopack.com"
    },
    "delivery_schedule": {
      "monday": "",
      "tuesday": "",
      "wednesday": "",
      "thursday": "",
      "friday": "",
      "saturday": ""
    },
    "settings": {
      "webshop_enabled": false,
      "ds_addresses": false,
      "no_pickup_app": false,
      "minimum_order_value": null,
      "articles_not_in_history": ""
    },
    "additional_addresses": [
      {
        "address_number": "0",
        "salutation": "Firma",
        "name": "Storopack Deutschland GmbH & Ko.KG",
        "name3": "",
        "street": "Asbrookdamm 40",
        "city": "Hamburg",
        "postal_code": "22115",
        "country": "Deutschland",
        "phone": "(0 40) 40 71 59 90",
        "fax": "(0 40) 4 07 15 99 44",
        "email": "andre.boge@storopack.com",
        "is_default_billing": true,
        "is_default_delivery": true
      }
    ]
  },
  "order_statistics": {
    "total_orders": 0,
    "unique_articles_ordered": 0,
    "recent_orders_count": 0,
    "last_order_date": null
  },
  "order_history": []
}